quantum6g/QCNN.py
quantum6g/QKNN.py
quantum6g/__init__.py
quantum6g/quantum6g.py
tests/__init__.py
tests/test.py
quantum6g-1.3.0.dist-info/METADATA
quantum6g-1.3.0.dist-info/WHEEL
quantum6g-1.3.0.dist-info/top_level.txt
quantum6g-1.3.0.dist-info/RECORD
