Metadata-Version: 2.1
Name: quantum6g
Version: 1.3.0
Summary: This library is an automatic artificial intelligence library that combines Quantum and 6G technologies.
Home-page: https://github.com/quantumpiya/quantum6g
Author: Quantum PIYA
Author-email: emirhan@piya.ai
Keywords: quantum machine-learning,quantum cnn,qcnn,quantum convolutional neural network,quantum 6g,6g,quantum,AI,quantum neural networks,qnn,quantum ai,artificial intelligence
Requires-Dist: numpy
Requires-Dist: tensorflow
Requires-Dist: pennylane
